charloratools/FilterAI.py
charloratools/Scrapers.py
charloratools/SysFileManager.py
charloratools/__init__.py
charloratools/cli.py
charloratools/errors.py
charloratools/utils.py
charloratools/facenet_pytorch/.git
charloratools/facenet_pytorch/.gitignore
charloratools/facenet_pytorch/.gitmodules
charloratools/facenet_pytorch/LICENSE.md
charloratools/facenet_pytorch/README.md
charloratools/facenet_pytorch/README_cn.md
charloratools/facenet_pytorch/__init__.py
charloratools/facenet_pytorch/codecov.yml
charloratools/facenet_pytorch/setup.py
charloratools/facenet_pytorch/.github/FUNDING.yml
charloratools/facenet_pytorch/.github/workflows/python.yml
charloratools/facenet_pytorch/data/.gitignore
charloratools/facenet_pytorch/data/facenet-pytorch-banner.png
charloratools/facenet_pytorch/data/multiface.jpg
charloratools/facenet_pytorch/data/multiface_detected.png
charloratools/facenet_pytorch/data/onet.pt
charloratools/facenet_pytorch/data/pnet.pt
charloratools/facenet_pytorch/data/rnet.pt
charloratools/facenet_pytorch/data/test_images/angelina_jolie/1.jpg
charloratools/facenet_pytorch/data/test_images/bradley_cooper/1.jpg
charloratools/facenet_pytorch/data/test_images/kate_siegel/1.jpg
charloratools/facenet_pytorch/data/test_images/paul_rudd/1.jpg
charloratools/facenet_pytorch/data/test_images/shea_whigham/1.jpg
charloratools/facenet_pytorch/data/test_images_aligned/angelina_jolie/1.png
charloratools/facenet_pytorch/data/test_images_aligned/bradley_cooper/1.png
charloratools/facenet_pytorch/data/test_images_aligned/kate_siegel/1.png
charloratools/facenet_pytorch/data/test_images_aligned/paul_rudd/1.png
charloratools/facenet_pytorch/data/test_images_aligned/shea_whigham/1.png
charloratools/facenet_pytorch/dependencies/facenet/.git
charloratools/facenet_pytorch/dependencies/facenet/.gitignore
charloratools/facenet_pytorch/dependencies/facenet/.project
charloratools/facenet_pytorch/dependencies/facenet/.pydevproject
charloratools/facenet_pytorch/dependencies/facenet/.pylintrc
charloratools-1.1.2.dist-info/LICENSE
charloratools-1.1.2.dist-info/METADATA
charloratools-1.1.2.dist-info/WHEEL
charloratools-1.1.2.dist-info/entry_points.txt
charloratools-1.1.2.dist-info/top_level.txt
charloratools-1.1.2.dist-info/RECORD
