Metadata-Version: 2.1
Name: charloratools
Version: 1.1.2
Summary: Python package including tools that facilitate training images scraping, management, and filtering for stable diffusion character LoRa training.
Author-email: svdC1 <svdc1mail@gmail.com>
Maintainer-email: svdC1 <svdc1mail@gmail.com>
License: MIT License
Project-URL: repository, https://github.com/svdC1/charloratools
Project-URL: documentation, https://svdc1.github.io/charloratools/
Classifier: Programming Language :: Python :: 3
Classifier: License :: OSI Approved :: MIT License
Classifier: Operating System :: OS Independent
Requires-Python: >=3.11
License-File: LICENSE
Requires-Dist: numpy<2.0.0,>=1.24.0
Requires-Dist: requests<3.0.0,>=2.0.0
Requires-Dist: Pillow<10.3.0,>=10.2.0
Requires-Dist: opencv-python<5.0.0,>=4.7
Requires-Dist: scipy<2.0.0,>=1.10.0
Requires-Dist: tqdm<5.0.0,>=4.0.0
Requires-Dist: pandas<3.0.0,>=2.0.0
Requires-Dist: imagehash>=4.0.0
Requires-Dist: selenium<5.0.0,>=4.8.0
Requires-Dist: webdriver-manager>=3.0.0
Requires-Dist: onnx>=1.14.0
Requires-Dist: matplotlib<4.0.0,>=3.5.0
Requires-Dist: scikit-learn<2.0.0,>=1.2.0
Requires-Dist: scikit-image<1.0.0,>=0.19.0
Requires-Dist: easydict
Requires-Dist: cython>=3.0.2
Requires-Dist: albumentations<2.0.0,>=1.2.0
Requires-Dist: prettytable
Requires-Dist: coloredlogs>=15.0
Requires-Dist: flatbuffers>=23.3.3
Provides-Extra: cpu
Requires-Dist: torch; extra == "cpu"
Requires-Dist: torchvision; extra == "cpu"
Requires-Dist: torchaudio; extra == "cpu"
Provides-Extra: dev
Requires-Dist: coverage<8.0.0,>=7.0.0; extra == "dev"
Requires-Dist: codecov<3.0.0,>=2.0.0; extra == "dev"
Requires-Dist: jupyter>=1.0.0; extra == "dev"
Requires-Dist: pytest; extra == "dev"
Requires-Dist: flake8; extra == "dev"
Requires-Dist: black; extra == "dev"
Provides-Extra: docs
Requires-Dist: black; extra == "docs"
Requires-Dist: mkdocs; extra == "docs"
Requires-Dist: mkdocstrings; extra == "docs"
Requires-Dist: mkdocstrings-python; extra == "docs"
Requires-Dist: mkdocs-autorefs; extra == "docs"
Requires-Dist: mkdocs-get-deps; extra == "docs"
Requires-Dist: mkdocs-material>9.5.0; extra == "docs"
Requires-Dist: mkdocs-material-extensions; extra == "docs"
Requires-Dist: markdown; extra == "docs"
Requires-Dist: pymdown-extensions; extra == "docs"
Requires-Dist: Pygments; extra == "docs"
